Metadata-Version: 2.1
Name: pynextflow
Version: 0.1
Summary: Nextflow pipelines with Python
Author: Jordi Deu-Pons
License: MPL-2
Keywords: pipeline,workflow
Platform: UNKNOWN
